notion_model/__init__.py
notion_model/_core.py
notion_model/_types.py
notion_model/_version.py
notion_model-0.0.5.dist-info/METADATA
notion_model-0.0.5.dist-info/WHEEL
notion_model-0.0.5.dist-info/RECORD
