Metadata-Version: 2.4
Name: notion-model
Version: 0.0.5
Project-URL: homepage, https://todo.com
Project-URL: source, https://todo.com
Project-URL: download, https://todo.com
Project-URL: changelog, https://todo.com
Project-URL: releasenotes, https://todo.com
Project-URL: documentation, https://todo.com
Project-URL: issues, https://todo.com
Project-URL: funding, https://todo.com
Author-email: Austin Yu <yuxm.austin1023@gmail.com>
Maintainer-email: Austin Yu <yuxm.austin1023@gmail.com>
License-Expression: MIT
Requires-Python: >=3.10
Requires-Dist: aiohttp>=3.12.15
Requires-Dist: pydantic>=2.11.7
Requires-Dist: requests>=2.32.4
